zenith/__init__.py
zenith/components/__init__.py
zenith/components/pod.py
zenith/components/pool.py
zenith/ext/__init__.py
zenith/ext/exceptions.py
zenith/ext/singleton.py
zenith/services/__init__.py
zenith/services/pool_registry.py
zenith/stats/__init__.py
zenith/stats/permission.py
nyria_zenith-1.1.0.dist-info/LICENSE
nyria_zenith-1.1.0.dist-info/METADATA
nyria_zenith-1.1.0.dist-info/WHEEL
nyria_zenith-1.1.0.dist-info/top_level.txt
nyria_zenith-1.1.0.dist-info/RECORD
